fastapi_peewee_filter/__init__.py
fastapi_peewee_filter-0.0.1.dist-info/METADATA
fastapi_peewee_filter-0.0.1.dist-info/WHEEL
fastapi_peewee_filter-0.0.1.dist-info/top_level.txt
fastapi_peewee_filter-0.0.1.dist-info/RECORD
