Metadata-Version: 2.1
Name: fastapi-peewee-filter
Version: 0.0.1
Summary: fastapi+peewee support
Home-page: https://github.com/ponponon/fastapi-peewee-filter
Author: ponponon
Author-email: 1729303158@qq.com
Maintainer: ponponon
Maintainer-email: 1729303158@qq.com
License: MIT License
Platform: all
Classifier: Programming Language :: Python
Classifier: Operating System :: MacOS :: MacOS X
Classifier: Operating System :: POSIX
Classifier: Programming Language :: Python :: 3
Classifier: Programming Language :: Python :: 3.8
Classifier: Programming Language :: Python :: 3.9
Classifier: Programming Language :: Python :: 3.10
Classifier: Programming Language :: Python :: 3.11
Classifier: Topic :: Internet
Classifier: Topic :: Software Development :: Libraries :: Python Modules
Classifier: Intended Audience :: Developers
Requires-Dist: peewee
Requires-Dist: fastapi
